{"Mercy Robertson": {"network": 2, "full_name": "Mercy Robertson", "employed": true, "wealth": 0, "gender": "f", "ambition": 5, "position": "Keeper of the King's Weasels", "full_title": null, "intel": 5, "extended_title": "Mercy Robertson the younger"}, "Tycho Jogioja": {"network": 3, "full_name": "Tycho Jogioja", "employed": false, "wealth": 5, "gender": "m", "ambition": 4, "full_title": "Marquis of Buckingham Shed", "intel": 5, "extended_title": "Tycho Jogioja the wizard, Marquis of Buckingham Shed"}, "Stevedave Hatchet": {"network": 6, "full_name": "Stevedave Hatchet", "ambition": 4, "wealth": 2, "gender": "m", "employed": false, "full_title": "Lord of Murderville", "intel": 5, "extended_title": "Stevedave Hatchet the misspeled, Lord of Murderville"}, "Beka Callarman-Williams": {"network": 4, "full_name": "Beka Callarman-Williams", "ambition": 3, "wealth": 6, "gender": "f", "employed": false, "full_title": "Baroness of Disneyland", "intel": 6, "extended_title": "Beka Callarman-Williams the bastard, Baroness of Disneyland"}, "Mercy Vimes": {"network": 7, "full_name": "Mercy Vimes", "ambition": 9, "wealth": 5, "gender": "f", "employed": false, "full_title": "Chief of Imagination", "intel": 6, "extended_title": "Mercy Vimes the six year old, Chief of Imagination"}, "Tim \"The rock\" Mcgruffy": {"network": 3, "full_name": "Tim \"The rock\" Mcgruffy", "employed": false, "wealth": 3, "gender": "m", "ambition": 7, "full_title": null, "intel": 7, "extended_title": "Tim \"The rock\" Mcgruffy the motionless"}, "Tycho Sonson": {"network": 7, "full_name": "Tycho Sonson", "ambition": 7, "wealth": 5, "gender": "m", "employed": false, "full_title": "Baron of Space", "intel": 5, "extended_title": "Tycho Sonson the Eternal, Baron of Space"}, "Ingrid \"The rock\" Mcgruffy": {"network": 8, "full_name": "Ingrid \"The rock\" Mcgruffy", "ambition": 8, "wealth": 7, "gender": "f", "employed": false, "full_title": "Earl of the view from Pride Rock", "intel": 7, "extended_title": "Ingrid \"The rock\" Mcgruffy the smartass, Earl of the view from Pride Rock"}, "Rob \"The rock\" Mcgruffy": {"network": 7, "full_name": "Rob \"The rock\" Mcgruffy", "ambition": 3, "wealth": 7, "gender": "m", "employed": false, "full_title": "Earl of Mars", "intel": 3, "extended_title": "Rob \"The rock\" Mcgruffy the cheapskate, Earl of Mars"}, "Megan Morrice": {"network": 7, "full_name": "Megan Morrice", "employed": false, "wealth": 5, "gender": "f", "ambition": 5, "extended_title": "Megan Morrice the flake, Lady of New South Wales", "intel": 6, "full_title": "Lady of New South Wales"}, "Pauline Windsor": {"network": 2, "full_name": "Pauline Windsor", "employed": true, "wealth": 3, "gender": "f", "ambition": 0, "position": "The King's second best cook", "full_title": null, "intel": 2, "extended_title": "Pauline Windsor the undescribable"}, "Elizabeth Jogioja": {"network": 5, "full_name": "Elizabeth Jogioja", "employed": false, "wealth": 4, "gender": "f", "ambition": 5, "full_title": "Lady of Disneyland", "intel": 5, "extended_title": "Elizabeth Jogioja the obviously fictional, Lady of Disneyland"}, "Sam Leech": {"network": 6, "full_name": "Sam Leech", "employed": true, "wealth": 4, "gender": "m", "ambition": 4, "position": "Official Boot Licker", "full_title": "Count of all floors, everywhere", "intel": 6, "extended_title": "Sam Leech the smartass, Count of all floors, everywhere"}, "David Murdery": {"network": 9, "full_name": "David Murdery", "employed": false, "wealth": 1, "gender": "m", "ambition": 6, "extended_title": "David Murdery the crow, Earl of the barren north", "intel": 4, "full_title": "Earl of the barren north"}, "Ingrid Puddleson": {"network": 4, "full_name": "Ingrid Puddleson", "ambition": 6, "wealth": 8, "gender": "f", "employed": false, "full_title": "Chief of 12 Forrester Walk, Milton Keynes, MK10 9TN", "intel": 6, "extended_title": "Ingrid Puddleson the misspeled, Chief of 12 Forrester Walk, Milton Keynes, MK10 9TN"}}